ui_coverage_scenario_tool/__init__.py
ui_coverage_scenario_tool/config.py
ui_coverage_scenario_tool/cli/__init__.py
ui_coverage_scenario_tool/cli/main.py
ui_coverage_scenario_tool/cli/commands/__init__.py
ui_coverage_scenario_tool/cli/commands/copy_report.py
ui_coverage_scenario_tool/cli/commands/print_config.py
ui_coverage_scenario_tool/cli/commands/save_report.py
ui_coverage_scenario_tool/src/__init__.py
ui_coverage_scenario_tool/src/coverage/__init__.py
ui_coverage_scenario_tool/src/coverage/builder.py
ui_coverage_scenario_tool/src/coverage/models.py
ui_coverage_scenario_tool/src/history/__init__.py
ui_coverage_scenario_tool/src/history/builder.py
ui_coverage_scenario_tool/src/history/models.py
ui_coverage_scenario_tool/src/history/storage.py
ui_coverage_scenario_tool/src/reports/__init__.py
ui_coverage_scenario_tool/src/reports/models.py
ui_coverage_scenario_tool/src/reports/storage.py
ui_coverage_scenario_tool/src/reports/templates/index.html
ui_coverage_scenario_tool/src/tools/__init__.py
ui_coverage_scenario_tool/src/tools/actions.py
ui_coverage_scenario_tool/src/tools/logger.py
ui_coverage_scenario_tool/src/tools/selector.py
ui_coverage_scenario_tool/src/tools/types.py
ui_coverage_scenario_tool/src/tracker/__init__.py
ui_coverage_scenario_tool/src/tracker/core.py
ui_coverage_scenario_tool/src/tracker/storage.py
ui_coverage_scenario_tool/src/tracker/models/__init__.py
ui_coverage_scenario_tool/src/tracker/models/elements.py
ui_coverage_scenario_tool/src/tracker/models/pages.py
ui_coverage_scenario_tool/src/tracker/models/scenarios.py
ui_coverage_scenario_tool/src/tracker/models/transitions.py
ui_coverage_scenario_tool-0.17.0.dist-info/licenses/LICENSE
ui_coverage_scenario_tool-0.17.0.dist-info/METADATA
ui_coverage_scenario_tool-0.17.0.dist-info/WHEEL
ui_coverage_scenario_tool-0.17.0.dist-info/entry_points.txt
ui_coverage_scenario_tool-0.17.0.dist-info/top_level.txt
ui_coverage_scenario_tool-0.17.0.dist-info/RECORD
