Metadata-Version: 2.4
Name: ui-coverage-scenario-tool
Version: 0.17.0
Summary: UI Coverage Tool is an innovative, no-overhead solution for tracking and visualizing UI test coverage — directly on your actual application, not static snapshots.
Home-page: https://github.com/Nikita-Filonov/ui-coverage-scenario-tool
Author: Nikita Filonov
Author-email: filonov.nikitkaa@gmail.com
Project-URL: Bug Tracker, https://github.com/Nikita-Filonov/ui-coverage-scenario-tool/issues
Classifier: Programming Language :: Python :: 3
Classifier: License :: OSI Approved :: MIT License
Classifier: Operating System :: OS Independent
Requires-Python: >=3.11
License-File: LICENSE
Requires-Dist: click
Requires-Dist: pyyaml>=6.0.2
Requires-Dist: pydantic>=2.0.0
Requires-Dist: pydantic-settings>=2.8.0
Dynamic: author
Dynamic: author-email
Dynamic: classifier
Dynamic: description
Dynamic: description-content-type
Dynamic: home-page
Dynamic: license-file
Dynamic: project-url
Dynamic: requires-dist
Dynamic: requires-python
Dynamic: summary
